laser_offset/__init__.py
laser_offset/__main__.py
laser_offset/cli/laser_offset_cli.py
laser_offset/exporters/dxf_exporter.py
laser_offset/exporters/exporter.py
laser_offset/exporters/svg_exporter.py
laser_offset/file_converters/file_converter.py
laser_offset/file_converters/folder_converter.py
laser_offset/geometry_2d/angle_range.py
laser_offset/geometry_2d/arc_info.py
laser_offset/geometry_2d/arc_segment_2d.py
laser_offset/geometry_2d/bounds2d.py
laser_offset/geometry_2d/bounds_rect_2d.py
laser_offset/geometry_2d/canvas2d.py
laser_offset/geometry_2d/fill_style.py
laser_offset/geometry_2d/normalize_angle.py
laser_offset/geometry_2d/point2d.py
laser_offset/geometry_2d/segment_2d.py
laser_offset/geometry_2d/shape2d.py
laser_offset/geometry_2d/size2d.py
laser_offset/geometry_2d/stroke_style.py
laser_offset/geometry_2d/style2d.py
laser_offset/geometry_2d/vector2d.py
laser_offset/geometry_2d/shapes_2d/arc2d.py
laser_offset/geometry_2d/shapes_2d/bezier2d.py
laser_offset/geometry_2d/shapes_2d/circle2d.py
laser_offset/geometry_2d/shapes_2d/ellipse2d.py
laser_offset/geometry_2d/shapes_2d/line2d.py
laser_offset/geometry_2d/shapes_2d/path2d.py
laser_offset/geometry_2d/shapes_2d/polygon2d.py
laser_offset/geometry_2d/shapes_2d/polyline2d.py
laser_offset/geometry_2d/shapes_2d/rect2d.py
laser_offset/importers/dxf_importer.py
laser_offset/importers/importer.py
laser_offset/importers/svg_importer.py
laser_offset/math/float_functions.py
laser_offset/modifiers/expand.py
laser_offset/modifiers/modifier.py
laser_offset/modifiers/polygon_data.py
laser_offset/modifiers/segment_operations.py
laser_offset-0.7.0.dist-info/LICENSE
laser_offset-0.7.0.dist-info/METADATA
laser_offset-0.7.0.dist-info/WHEEL
laser_offset-0.7.0.dist-info/entry_points.txt
laser_offset-0.7.0.dist-info/top_level.txt
laser_offset-0.7.0.dist-info/RECORD
