Metadata-Version: 2.1
Name: laser-offset
Version: 0.7.0
Summary: Simple Tools that creates external and internal offsets for shapes. Supports DXF and SVG Import/Export.
Author-email: Andrey Zarembo-Godzyatskiy <andrey.zarembo@gmail.com>
Project-URL: Homepage, https://github.com/AndreyZarembo/LaserOffset
Project-URL: Bug Tracker, https://github.com/AndreyZarembo/LaserOffset/issues
Classifier: Programming Language :: Python :: 3
Classifier: License :: OSI Approved :: MIT License
Classifier: Operating System :: OS Independent
Requires-Python: >=3.7
License-File: LICENSE
